opbeat-3.6.1.dist-info/metadata.json
opbeat-3.6.1.dist-info/WHEEL
opbeat-3.6.1.dist-info/top_level.txt
opbeat-3.6.1.dist-info/DESCRIPTION.rst
opbeat-3.6.1.dist-info/METADATA
opbeat-3.6.1.dist-info/RECORD
opbeat-3.6.1.dist-info/entry_points.txt
tests/handlers/__init__.py
tests/handlers/logging/__init__.py
tests/handlers/logging/logging_tests.py
tests/handlers/logbook/logbook_tests.py
tests/handlers/logbook/__init__.py
tests/transports/test_http.py
tests/transports/__init__.py
tests/transports/test_urllib3.py
tests/config/__init__.py
tests/config/tests.py
tests/contrib/__init__.py
tests/contrib/flask/flask_tests.py
tests/contrib/flask/__init__.py
tests/contrib/celery/__init__.py
tests/contrib/celery/tests.py
tests/contrib/django/__init__.py
tests/contrib/django/django_tests.py
tests/contrib/django/fake1/__init__.py
tests/contrib/django/testapp/__init__.py
tests/contrib/django/testapp/urls.py
tests/contrib/django/testapp/models.py
tests/contrib/django/testapp/views.py
tests/contrib/django/testapp/middleware.py
tests/contrib/django/testapp/celery.py
tests/contrib/django/fake2/__init__.py
tests/contrib/twisted/__init__.py
tests/contrib/twisted/tests.py
tests/contrib/zerorpc/__init__.py
tests/contrib/zerorpc/zeropc_tests.py
tests/contrib/async/__init__.py
tests/contrib/async/tests.py
tests/contrib/pylons/__init__.py
tests/contrib/pylons/tests.py
tests/events/__init__.py
tests/events/tests.py
tests/processors/__init__.py
tests/processors/tests.py
tests/instrumentation/dbapi2_tests.py
tests/instrumentation/python_memcached_tests.py
tests/instrumentation/sqlite_tests.py
tests/instrumentation/botocore_tests.py
tests/instrumentation/pymongo_tests.py
tests/instrumentation/base_tests.py
tests/instrumentation/__init__.py
tests/instrumentation/psycopg2_tests.py
tests/instrumentation/requests_tests.py
tests/instrumentation/redis_tests.py
tests/instrumentation/mysql_tests.py
tests/instrumentation/urllib3_tests.py
tests/instrumentation/request_store_tests.py
tests/instrumentation/jinja2_tests/__init__.py
tests/instrumentation/jinja2_tests/jinja2_tests.py
tests/instrumentation/django_tests/__init__.py
tests/instrumentation/django_tests/template_tests.py
