Metadata-Version: 2.0
Name: opbeat
Version: 3.6.1
Summary: The official Python module for Opbeat.com
Home-page: https://github.com/opbeat/opbeat_python
Author: Opbeat, Inc
Author-email: support@opbeat.com
License: UNKNOWN
Platform: UNKNOWN
Classifier: Intended Audience :: Developers
Classifier: Intended Audience :: System Administrators
Classifier: Operating System :: OS Independent
Classifier: Topic :: Software Development
Classifier: Programming Language :: Python
Classifier: Programming Language :: Python :: 2.7
Classifier: Programming Language :: Python :: 3.3
Classifier: Programming Language :: Python :: 3.4
Classifier: Programming Language :: Python :: 3.5
Classifier: Programming Language :: Python :: 3.6
Requires-Dist: urllib3
Requires-Dist: certifi
Provides-Extra: asyncio
Requires-Dist: aiohttp; extra == 'asyncio'
Provides-Extra: flask
Requires-Dist: blinker; extra == 'flask'
Provides-Extra: tests
Requires-Dist: py (>=1.4.26); extra == 'tests'
Requires-Dist: pytest (>=2.6.4); extra == 'tests'
Requires-Dist: pytest-django (==2.8.0); extra == 'tests'
Requires-Dist: pytest-capturelog (>=0.7); extra == 'tests'
Requires-Dist: blinker (>=1.1); extra == 'tests'
Requires-Dist: celery; extra == 'tests'
Requires-Dist: django-celery; extra == 'tests'
Requires-Dist: Flask (>=0.8); extra == 'tests'
Requires-Dist: logbook; extra == 'tests'
Requires-Dist: mock; extra == 'tests'
Requires-Dist: pep8; extra == 'tests'
Requires-Dist: webob; extra == 'tests'
Requires-Dist: pytz; extra == 'tests'
Requires-Dist: redis; extra == 'tests'
Requires-Dist: requests; extra == 'tests'
Requires-Dist: jinja2; extra == 'tests'
Requires-Dist: pytest-benchmark; extra == 'tests'
Requires-Dist: urllib3-mock; extra == 'tests'
Requires-Dist: Twisted; extra == 'tests'
Requires-Dist: apipkg; extra == 'tests'
Requires-Dist: execnet; extra == 'tests'
Requires-Dist: isort; extra == 'tests'
Requires-Dist: pytest-cache; extra == 'tests'
Requires-Dist: pytest-isort; extra == 'tests'
Requires-Dist: python3-memcached; extra == 'tests'
Requires-Dist: Django (>=1.2); extra == 'tests'
Requires-Dist: psycopg2; extra == 'tests'
